ezcrowdcount/__init__.py
ezcrowdcount/__main__.py
ezcrowdcount/crowd_count.py
ezcrowdcount/models.py
ezcrowdcount/network.py
ezcrowdcount/utils.py
ezcrowdcount-1.0.0.dist-info/LICENSE
ezcrowdcount-1.0.0.dist-info/METADATA
ezcrowdcount-1.0.0.dist-info/WHEEL
ezcrowdcount-1.0.0.dist-info/entry_points.txt
ezcrowdcount-1.0.0.dist-info/top_level.txt
ezcrowdcount-1.0.0.dist-info/RECORD
