Metadata-Version: 2.1
Name: ezcrowdcount
Version: 1.0.0
Summary: Easy to integrate Crowd Counting Library
Author-email: Ahmed Heakl <ahmed.heakl@ejust.edu.eg>
Project-URL: repository, https://github.com/ahmedheakl/crowdcount
Keywords: crowd counting,computer vision,object recognition,human counting,pytorch,thread
Classifier: License :: OSI Approved :: MIT License
Classifier: Programming Language :: Python
Classifier: Programming Language :: Python :: 3
Requires-Python: >=3.7
License-File: LICENSE
Requires-Dist: numpy
Requires-Dist: opencv-python
Requires-Dist: torch
Requires-Dist: h5py
Requires-Dist: googledrivedownloader
Requires-Dist: requests
Provides-Extra: build
Requires-Dist: build ; extra == 'build'
Requires-Dist: twine ; extra == 'build'
Provides-Extra: dev
Requires-Dist: black ; extra == 'dev'
Requires-Dist: bumpver ; extra == 'dev'
